alignsar/Meta_info_extraction_global_local.py
alignsar/__init__.py
alignsar/alignsar_utils.py
alignsar/resdata.py
alignsar/signature_extraction.py
alignsar/bin/convert_ll2ra.sh
alignsar/bin/export2tif_rd_snap.sh
alignsar/bin/geocode_ifg_snap.sh
alignsar/rdrcode/__init__.py
alignsar/rdrcode/rdrCode_main.py
alignsar/rdrcode/rdrCode_prep_ref_data.py
alignsar/rdrcode/snap_rdrcode.py
alignsar/stac/__init__.py
alignsar/stac/convert.py
alignsar/stac/gcps.py
alignsar/stac/georeference.py
alignsar/stac/points.py
alignsar-1.1.7.data/scripts/convert_ll2ra.sh
alignsar-1.1.7.data/scripts/export2tif_rd_snap.sh
alignsar-1.1.7.data/scripts/geocode_ifg_snap.sh
alignsar-1.1.7.dist-info/licenses/LICENSE
alignsar-1.1.7.dist-info/METADATA
alignsar-1.1.7.dist-info/WHEEL
alignsar-1.1.7.dist-info/entry_points.txt
alignsar-1.1.7.dist-info/top_level.txt
alignsar-1.1.7.dist-info/RECORD
