Metadata-Version: 2.4
Name: alignsar
Version: 1.1.7
Summary: AlignSAR: An open-source toolbox of SAR benchmark dataset creation for machine learning applications
Author: Xu Zhang, Anurag Kulshrestha, Milan Lazecky, Serkan Girgin, Jose Manuel Delgado Blasco
Author-email: Ling Chang <ling.chang@utwente.nl>
License: 
Project-URL: Repository, https://github.com/Bingquan-InSAR/alignSAR
Project-URL: Issues, https://github.com/Bingquan-InSAR/alignSAR/issues
Keywords: SAR,Benchmark Datasets,Machine Learning
Classifier: Intended Audience :: Science/Research
Classifier: License :: OSI Approved :: Apache Software License
Classifier: Natural Language :: English
Classifier: Programming Language :: Python :: 3.10
Requires-Python: >=3.8
License-File: LICENSE
Requires-Dist: numpy>=1.22
Requires-Dist: scipy>=1.8
Requires-Dist: scikit-learn>=1.1
Requires-Dist: xarray>=2022.03
Requires-Dist: netCDF4>=1.6
Requires-Dist: matplotlib>=3.5
Provides-Extra: dev
Requires-Dist: pytest>=7; extra == "dev"
Requires-Dist: pytest-cov>=4; extra == "dev"
Requires-Dist: ruff>=0.5; extra == "dev"
Requires-Dist: mypy>=1.7; extra == "dev"
Requires-Dist: pre-commit>=3.5; extra == "dev"
Dynamic: license-file
